turtle4t/__init__.py
turtle4t/turtle.cfg
海龜模組/__init__.py
turtle4t-0.0.3.dist-info/METADATA
turtle4t-0.0.3.dist-info/WHEEL
turtle4t-0.0.3.dist-info/top_level.txt
turtle4t-0.0.3.dist-info/RECORD
