Metadata-Version: 2.1
Name: turtle4t
Version: 0.0.3
Summary: turtle for Teenagers
Home-page: https://github.com/beardad1975/turtle4t
Author: Wen-Hung, Chang 張文宏
Author-email: beardad1975@nmes.tyc.edu.tw
License: UNKNOWN
Platform: Windows
Classifier: Programming Language :: Python :: 3
Classifier: License :: OSI Approved :: MIT License
Classifier: Operating System :: Microsoft :: Windows
Classifier: Natural Language :: Chinese (Traditional)
Requires-Python: >=3.5
